ionit_plugin.py
ionit-0.5.1.data/scripts/ionit
usr/lib/systemd/system/ionit.service
ionit-0.5.1.dist-info/LICENSE
ionit-0.5.1.dist-info/METADATA
ionit-0.5.1.dist-info/WHEEL
ionit-0.5.1.dist-info/top_level.txt
ionit-0.5.1.dist-info/RECORD
