Metadata-Version: 2.1
Name: ionit
Version: 0.5.1
Summary: Render configuration files from Jinja templates
Home-page: https://github.com/bdrung/ionit
Author: Benjamin Drung
Author-email: bdrung@posteo.de
License: ISC
Project-URL: Bug Tracker, https://github.com/bdrung/ionit/issues
Classifier: Development Status :: 5 - Production/Stable
Classifier: Environment :: Console
Classifier: License :: OSI Approved :: ISC License (ISCL)
Classifier: Operating System :: POSIX
Classifier: Programming Language :: Python :: 3
Classifier: Programming Language :: Python :: 3 :: Only
Classifier: Programming Language :: Python :: 3.6
Classifier: Programming Language :: Python :: 3.7
Classifier: Programming Language :: Python :: 3.8
Classifier: Programming Language :: Python :: 3.9
Requires-Python: >=3.6
License-File: LICENSE
Requires-Dist: PyYAML
Requires-Dist: jinja2
